{"lines":[{"category":"Clothing","class":"clothing","lastname":"Kemeza","firstname":"Christopher","business":"The Free and Rowdy","url":"thefreeandrowdy.com"},{"category":"Clothing","class":"clothing","lastname":"Musngi","firstname":"Maria","business":"ORB Clothing","url":"orbclothing.etsy.com"},{"category":"Clothing","class":"clothing","lastname":"Rothshild","firstname":"Sharon","business":"Two Stix","url":"www.twostixthestore.com"},{"category":"Decorative","class":"decorative","lastname":"Cutts","firstname":"Creighton","business":"Bee Natural","url":"www.teenatural.com"},{"category":"Decorative","class":"decorative","lastname":"Fortenberry","firstname":"Jimmy","business":"Sealife Creation","url":"www.theamazingjellyfish.com"},{"category":"Decorative","class":"decorative","lastname":"Hilton","firstname":"Katja","business":"Amazing & Beautiful Butterflies","url":"www.abbutterflies.com"},{"category":"Decorative","class":"decorative","lastname":"Pun","firstname":"Patty","business":"Jute Sculptures","url":""},{"category":"Decorative","class":"decorative","lastname":"Yancey-Willis","firstname":"Kira","business":"Kira Yancey-Willis Ceramics","url":""},{"category":"Fiber","class":"fiber","lastname":"Borden","firstname":"Richard","business":"Shibumi Silks","url":"www.facebook.com/ShibumiSilks"},{"category":"Fiber","class":"fiber","lastname":"Kosmicki","firstname":"Anne","business":"2 City Studio","url":"www.twocitystudio.com"},{"category":"Fiber","class":"fiber","lastname":"Masters","firstname":"Nikita","business":"Nikita Lynn Designs","url":"www.nikitalynn.com"},{"category":"Fiber","class":"fiber","lastname":"Matzkin","firstname":"Susan","business":"Silk Art Co.","url":"www.facebook.com/silkartco"},{"category":"Fiber","class":"fiber","lastname":"Raymond","firstname":"Lorri","business":"Lulabella Designs","url":"lulabelladesigns.com"},{"category":"Fiber","class":"fiber","lastname":"Wicher","firstname":"Carolyn","business":"Carolyn Wicher Silk Studio","url":""},{"category":"Fiber","class":"fiber","lastname":"Wise","firstname":"Lisa","business":"Re:loom weaving a better life","url":"www.reloom.org"},{"category":"Fiber","class":"fiber","lastname":"Yang","firstname":"May","business":"May's Stitchery","url":""},{"category":"Furniture","class":"furniture","lastname":"Courts","firstname":"Michael","business":"McMeubel LLC","url":"www.mcmeubel.com"},{"category":"Furniture","class":"furniture","lastname":"Oaks","firstname":"Chris","business":"Twin Oaks Hammocks","url":""},{"category":"Garden","class":"garden","lastname":"Heard","firstname":"Rick","business":"Garden Originals","url":""},{"category":"Garden","class":"garden","lastname":"Hopkins","firstname":"Jimmy & Marlene","business":"Creative Creations","url":"www.steelmenagerie.com"},{"category":"Garden","class":"garden","lastname":"Lee","firstname":"Nan-Hsiung","business":"Sweet Valley Nursery","url":""},{"category":"Garden","class":"garden","lastname":"Redgrave","firstname":"Michael","business":"Full Moon Bonsai","url":"www.bonsaimoon.com"},{"category":"Glass","class":"glass","lastname":"Frangi","firstname":"Jennifer","business":"Notorious Glass Women","url":"www.frangiglass.com"},{"category":"Glass","class":"glass","lastname":"Hagstrom","firstname":"Debbie","business":"Deborah Hagstrom Designs","url":""},{"category":"Glass","class":"glass","lastname":"Janke","firstname":"Matt","business":"Janke Studios, Inc.","url":"www.jankestudios.com"},{"category":"Glass","class":"glass","lastname":"Keeler","firstname":"Kyle","business":"Visionary Glass Arts","url":"www.visionaryglassarts.com"},{"category":"Glass","class":"glass","lastname":"Staley","firstname":"Susan","business":"Glass Treasures","url":""},{"category":"Glass","class":"glass","lastname":"Taylor","firstname":"Dan","business":"Oriskany Glass Studio","url":"www.oriskanyglass.etsy.com"},{"category":"Glass","class":"glass","lastname":"Victorica","firstname":"Andrea","business":"1550art","url":"www.1550art.com"},{"category":"Jewelry","class":"jewelry","lastname":"Bush","firstname":"Spirit","business":"Spirit Lala","url":"www.spiritlala.com"},{"category":"Jewelry","class":"jewelry","lastname":"Caldwell","firstname":"Treffry","business":"Pluma Jewelry","url":"www.plumajewelry.com"},{"category":"Jewelry","class":"jewelry","lastname":"Davis","firstname":"Faryn","business":"Fernworks","url":"www.fernworks.org"},{"category":"Jewelry","class":"jewelry","lastname":"Griffin","firstname":"Leigh","business":"Benchwork","url":"www.leighgriffinjewelry.com"},{"category":"Jewelry","class":"jewelry","lastname":"Haase","firstname":"Heather","business":"Heather Haase Designs","url":"www.heatherhaasedesigns.com"},{"category":"Jewelry","class":"jewelry","lastname":"Hicks","firstname":"Eric","business":"The Black Pearl","url":"facebook.com/theblackpearljewelry"},{"category":"Jewelry","class":"jewelry","lastname":"Hirt","firstname":"Jenna","business":"Tying Tribes","url":"tryingtribes.com"},{"category":"Jewelry","class":"jewelry","lastname":"Houndsome","firstname":"Jean","business":"Jeanique","url":"www.jeaniquejewelry.com"},{"category":"Jewelry","class":"jewelry","lastname":"Kidd","firstname":"Katherine","business":"KKIDD Designs","url":"www.kkidddesigns.com"},{"category":"Jewelry","class":"jewelry","lastname":"Kruse","firstname":"Cameron","business":"Cameron Kruse Designs","url":"www.cameronkruse.com"},{"category":"Jewelry","class":"jewelry","lastname":"Lambert","firstname":"Laura","business":"Laural Designs Jewelry","url":"www.lauraldesigns.com"},{"category":"Jewelry","class":"jewelry","lastname":"Lee","firstname":"Mary","business":"","url":"www.marysorigami.com"},{"category":"Jewelry","class":"jewelry","lastname":"McLean","firstname":"Sharon","business":"Zola Jewelry","url":"zolajewelry.com"},{"category":"Jewelry","class":"jewelry","lastname":"Miller","firstname":"Melanie","business":"The Alchemist`s Garden","url":"www.alchemistgarden.com"},{"category":"Jewelry","class":"jewelry","lastname":"Newman","firstname":"Rachael","business":"Trillium Designs","url":"www.trilliumdesigns.com"},{"category":"Jewelry","class":"jewelry","lastname":"Patrick","firstname":"Linda","business":"Laurindalee's Paper Bead Jewelry","url":"www.facebook.com/Laurindalees"},{"category":"Jewelry","class":"jewelry","lastname":"Roessler","firstname":"John","business":"Antique Spoon Jewelry","url":""},{"category":"Jewelry","class":"jewelry","lastname":"Ruang","firstname":"Wanpen and Tim","business":"Flower Jewelry","url":""},{"category":"Jewelry","class":"jewelry","lastname":"Sharp","firstname":"Jill","business":"Blue Piranha","url":"www.bpjewelry.com"},{"category":"Jewelry","class":"jewelry","lastname":"Simon","firstname":"Julie","business":"Jewels by Julie","url":"www.jewels-by-julie.com"},{"category":"Jewelry","class":"jewelry","lastname":"Smith","firstname":"Jamie","business":"Discarded and Gleaned","url":"www.discardedandgleaned.com/"},{"category":"Jewelry","class":"jewelry","lastname":"Stephens","firstname":"Jean","business":"Song Dog Studios","url":""},{"category":"Jewelry","class":"jewelry","lastname":"Thompson","firstname":"Delias","business":"Delias Studio","url":"www.deliasstudioinc.com"},{"category":"Leather","class":"leather","lastname":"Joyner","firstname":"Brian","business":"Hang Over Guitar Straps","url":"www.etsy.com/shop/HangOverGuitarStraps/"},{"category":"Leather","class":"leather","lastname":"Wye","firstname":"Jon","business":"Jon Wye","url":"www.jonwye.com"},{"category":"Metalcraft","class":"metalcraft","lastname":"Bergstrom","firstname":"Paul & Sue","business":"Mountain Melodies","url":"www.mtnmelodies.com"},{"category":"Metalcraft","class":"metalcraft","lastname":"Boone","firstname":"Maureen & Keith","business":"Rustic Attitudes","url":"www.rusticattitude.com"},{"category":"Metalcraft","class":"metalcraft","lastname":"Collins","firstname":"Chrissy","business":"Henna Works","url":""},{"category":"Metalcraft","class":"metalcraft","lastname":"Creekmur","firstname":"Nelms","business":"Nelms Creekmur  Forge","url":"www.nelmscreekmurforge.etsy.com"},{"category":"Metalcraft","class":"metalcraft","lastname":"Dorn","firstname":"Wayne","business":"Yardbirds","url":""},{"category":"Metalcraft","class":"metalcraft","lastname":"Hastings","firstname":"Janis","business":"Happy Face","url":"www.happyfaceentertainment.com"},{"category":"Metalcraft","class":"metalcraft","lastname":"Hoss","firstname":"Allen","business":"Allen Hoss Artworks","url":""},{"category":"Metalcraft","class":"metalcraft","lastname":"Keys","firstname":"Sarah Sctt","business":"","url":"www.sarahscottkeys.com"},{"category":"Metalcraft","class":"metalcraft","lastname":"Kimble","firstname":"Rosemary","business":"Henna Diva","url":"www.rosemaryi.com"},{"category":"Metalcraft","class":"metalcraft","lastname":"MacDonald","firstname":"Dave","business":"Macdonald Forge & Design","url":"www.bearwallowforge.com"},{"category":"Metalcraft","class":"metalcraft","lastname":"Walton","firstname":"Kathy","business":"Kathy Walton Art","url":"www.kathywaltonarts.com"},{"category":"Mixed Media","class":"mixed-media","lastname":"Alexandrin","firstname":"Anastasia","business":"Anastasia Fine Art","url":"aalexandrin.com"},{"category":"Mixed Media","class":"mixed-media","lastname":"Althafer","firstname":"Tyler","business":"Iron Zeppelin Productions","url":"www.ironzeppelin.com"},{"category":"Mixed Media","class":"mixed-media","lastname":"Bliss","firstname":"Dennis","business":"Dennis Bliss Art","url":"dennisblissart.com"},{"category":"Mixed Media","class":"mixed-media","lastname":"Corley","firstname":"Sonya","business":"Happyworks, A Design Studio","url":"www.happyworksdesignstudio.com"},{"category":"Mixed Media","class":"mixed-media","lastname":"Fesken","firstname":"John William","business":"","url":""},{"category":"Mixed Media","class":"mixed-media","lastname":"Keenan","firstname":"McKenzie","business":"McKenzie Keenan Designs","url":"www.mckenziekeenan.com/"},{"category":"Mixed Media","class":"mixed-media","lastname":"Land","firstname":"R.","business":"R Land Art","url":"www.rlandart.com"},{"category":"Mixed Media","class":"mixed-media","lastname":"Llew","firstname":"Houston","business":"Houston Llew, Inc.","url":"www.houstonllew.com"},{"category":"Mixed Media","class":"mixed-media","lastname":"McKenzie","firstname":"Shinita","business":"Wine Bottle Wicks","url":"www.wickedwinewicks.com/"},{"category":"Mixed Media","class":"mixed-media","lastname":"Rosemond II","firstname":"Keith","business":"Keith Two","url":"www.keithtwo.com"},{"category":"Mixed Media","class":"mixed-media","lastname":"Selph","firstname":"Doug","business":"Southern Botanics","url":"www.facebook.com/southernbotanics"},{"category":"Mixed Media","class":"mixed-media","lastname":"Snape","firstname":"Jason","business":"Snape Ridiculorum","url":"www.jasonsnape.com"},{"category":"Mixed Media","class":"mixed-media","lastname":"Tantillo","firstname":"Lisa","business":"Calou Calay","url":""},{"category":"Mixed Media","class":"mixed-media","lastname":"Xia","firstname":"Sompit","business":"Can Do Planes","url":"www.candoplanes.com"},{"category":"Painting","class":"painting","lastname":"Adams","firstname":"Cynthia & Steve","business":"Casa Art Studio","url":"www.casaartstudio.com"},{"category":"Painting","class":"painting","lastname":"Berroa","firstname":"Felix","business":"","url":"www.felixberroa.com"},{"category":"Painting","class":"painting","lastname":"Bolton","firstname":"Matt","business":"Matt Bolton Art","url":"www.facebook.com/MattBoltonArt"},{"category":"Painting","class":"painting","lastname":"Burns","firstname":"Thomas","business":"Atlanta Vintage Travel","url":"www.atlantavintagetravel.com"},{"category":"Painting","class":"painting","lastname":"Calkin","firstname":"Jamie","business":"","url":"www.jamiecalkin.com"},{"category":"Painting","class":"painting","lastname":"Coil","firstname":"Maria-Louise","business":"Maria-Louise Coil","url":"www.marialouise.com"},{"category":"Painting","class":"painting","lastname":"Coleman","firstname":"R Scott & Katherine","business":"","url":"thespringgallery.com"},{"category":"Painting","class":"painting","lastname":"Ferro","firstname":"Benito","business":"YoYo Ferro","url":"www.yoyoferro.com"},{"category":"Painting","class":"painting","lastname":"Flinn","firstname":"Sarah","business":"Art by Sarah Flinn","url":"www.sarahflinn.com"},{"category":"Painting","class":"painting","lastname":"Goldman","firstname":"David","business":"","url":"www.davegoldman.net"},{"category":"Painting","class":"painting","lastname":"Gullett","firstname":"Patsy","business":"Sculptured Watercolors","url":"www.sculpturedwatercolors.com"},{"category":"Painting","class":"painting","lastname":"Kosten","firstname":"Andrew","business":"Gum Pal Press","url":"www.andrewkosten.com"},{"category":"Painting","class":"painting","lastname":"McNeely","firstname":"Pat","business":"Pat McNeely Design","url":"www.patmcneely.com"},{"category":"Painting","class":"painting","lastname":"Paulsen","firstname":"Larry & Sherry","business":"City Art Market","url":"www.cityartmarket.com"},{"category":"Painting","class":"painting","lastname":"Prahler","firstname":"Michelle","business":"Planet Prahler","url":"www.planetprahler.com"},{"category":"Painting","class":"painting","lastname":"Riggan","firstname":"Jeff","business":"Monster Art Studio","url":"www.monsterartstudio.com"},{"category":"Painting","class":"painting","lastname":"Singleton","firstname":"R. Amber","business":"Amber Singleton Art and Design","url":"ambersingletonart.com"},{"category":"Painting","class":"painting","lastname":"Spoon","firstname":"","business":"Artwork By Spoon","url":"www.artworkbyspoon.com"},{"category":"Painting","class":"painting","lastname":"Stoddart Ladd","firstname":"Jessica","business":"Jessica Stoddart Ladd","url":"www.jessicastoddart.com"},{"category":"Painting","class":"painting","lastname":"Thomas","firstname":"Jason","business":"Red Rocket Farm","url":"www.redrocketfarm.com"},{"category":"Painting","class":"painting","lastname":"Webb","firstname":"Richard","business":"Such Like Studio LLC","url":"richardfwebb.com"},{"category":"Painting","class":"painting","lastname":"Wooster","firstname":"Anne D","business":"Anne Wooster Botanicals","url":"www.annewoosterimpressions.net"},{"category":"Photography","class":"photography","lastname":"Bryant","firstname":"Michael","business":"","url":"www.michael-bryant.com"},{"category":"Photography","class":"photography","lastname":"Burkhardt","firstname":"Bob","business":"PB&J Design","url":"www.pbjart.com"},{"category":"Photography","class":"photography","lastname":"Copeland","firstname":"Jim","business":"Jim Copeland Photography","url":"www.jimcopelandphotography.com"},{"category":"Photography","class":"photography","lastname":"Epstein","firstname":"Jana","business":"Jana Epstein Photography","url":"www.JanaEpstein.com"},{"category":"Photography","class":"photography","lastname":"von der Veen","firstname":"Mettina","business":"Photos by Mettina and AHI Imagines LLC","url":"www.photosbymettina.com"},{"category":"Photography","class":"photography","lastname":"Wolfe","firstname":"Kathy","business":"Kathy Wolfe Images","url":"www.kathywolfe.com"},{"category":"Pottery","class":"pottery","lastname":"Evans","firstname":"Brian P","business":"Evans Studios","url":"evanspottery.com"},{"category":"Pottery","class":"pottery","lastname":"Fields","firstname":"Norma","business":"The Harry Potters and Norma","url":""},{"category":"Pottery","class":"pottery","lastname":"Gilbert","firstname":"Cara","business":"Cara Gilbert Ceramics","url":"www.caragilbert.com"},{"category":"Pottery","class":"pottery","lastname":"Knapp","firstname":"Emily","business":"EK Studio","url":"www.ekstudioart.com"},{"category":"Pottery","class":"pottery","lastname":"Larson","firstname":"Haydn","business":"Haydn Larson Studios","url":"haydnlarsonstudios.com"},{"category":"Pottery","class":"pottery","lastname":"Lipscomb","firstname":"Ester","business":"Ester Lipscomb Pottery","url":"www.esterlipscomb.com"},{"category":"Pottery","class":"pottery","lastname":"Sherrill","firstname":"Polly","business":"Polly on the Avenue","url":"www.pollythepotter.com"},{"category":"Pottery","class":"pottery","lastname":"Strange","firstname":"Eric B","business":"Eric B Strange Pottery","url":"www.ericbstrangepottery.com"},{"category":"Sponsor","class":"sponsor","lastname":"Austin","firstname":"Marvin","business":"Super Green Solutions","url":""},{"category":"Woodcraft","class":"woodcraft","lastname":"Banh","firstname":"Timothy","business":"TB Archer Woodcrafts","url":""},{"category":"Woodcraft","class":"woodcraft","lastname":"Grimes","firstname":"Roger","business":"Kennesaw Woodpecker","url":"www.kennesawwoodpecker.com"},{"category":"Woodcraft","class":"woodcraft","lastname":"Kuhlman","firstname":"Tim","business":"KRCedar","url":"www.krcedar.com"},{"category":"Woodcraft","class":"woodcraft","lastname":"Little","firstname":"Andy & Christy","business":"The Write Stuff Pen Works","url":"www.custompenshop.com"},{"category":"Woodcraft","class":"woodcraft","lastname":"Malin","firstname":"Wendell","business":"Wendell`s Bowl","url":""},{"category":"Woodcraft","class":"woodcraft","lastname":"Mathew","firstname":"Richard","business":"Dixstyx","url":"www.etsy.com/shop/dixstyx"},{"category":"Woodcraft","class":"woodcraft","lastname":"McCollum","firstname":"Richard","business":"White Forest Spoons","url":"spootch.com"},{"category":"Woodcraft","class":"woodcraft","lastname":"Nelson","firstname":"Jeff","business":"Hudson River Inlay","url":"www.hudsonriverinlay.com"},{"category":"Woodcraft","class":"woodcraft","lastname":"Snowden","firstname":"Mike","business":"Snowden Guitars","url":"www.snowdenguitars.com"}]}